django_pdf_generator/__init__.py
django_pdf_generator/pdf_generator.py
django_pdf_generator/string_conversion.py
cpppackageAnuja-1.0.0.dist-info/METADATA
cpppackageAnuja-1.0.0.dist-info/WHEEL
cpppackageAnuja-1.0.0.dist-info/top_level.txt
cpppackageAnuja-1.0.0.dist-info/RECORD
