Metadata-Version: 2.1
Name: cpppackageAnuja
Version: 1.0.0
Summary: A short description of my package
Home-page: https://github.com/my_username/my_package
Author: Anuja
Author-email: anji9597@gmail.com
Classifier: Programming Language :: Python :: 3.11
Classifier: License :: OSI Approved :: MIT License
Classifier: Operating System :: OS Independent
Requires-Dist: requests (>=2.25.1)
Requires-Dist: numpy (>=1.19.5)
